genderbench/__init__.py
genderbench/config.py
genderbench/generators/__init__.py
genderbench/generators/anthropic_async_api.py
genderbench/generators/async_api.py
genderbench/generators/generator.py
genderbench/generators/open_ai_async_api.py
genderbench/generators/random.py
genderbench/harnesses/default.py
genderbench/probes/__init__.py
genderbench/probes/bbq/README.md
genderbench/probes/bbq/bbq_evaluator.py
genderbench/probes/bbq/bbq_metric_calculator.py
genderbench/probes/bbq/bbq_probe.py
genderbench/probes/business_vocabulary/README.md
genderbench/probes/business_vocabulary/business_vocabulary_evaluator.py
genderbench/probes/business_vocabulary/business_vocabulary_metric_calculator.py
genderbench/probes/business_vocabulary/business_vocabulary_probe.py
genderbench/probes/direct/README.md
genderbench/probes/direct/direct_metric_calculator.py
genderbench/probes/direct/direct_probe.py
genderbench/probes/discrimination_tamkin/README.md
genderbench/probes/discrimination_tamkin/discrimination_tamkin_genders.py
genderbench/probes/discrimination_tamkin/discrimination_tamkin_metric_calculator.py
genderbench/probes/discrimination_tamkin/discrimination_tamkin_probe.py
genderbench/probes/diversity_med_qa/README.md
genderbench/probes/diversity_med_qa/diversity_med_qa_evaluator.py
genderbench/probes/diversity_med_qa/diversity_med_qa_metric_calculator.py
genderbench/probes/diversity_med_qa/diversity_med_qa_probe.py
genderbench/probes/dreaddit/README.md
genderbench/probes/dreaddit/dreaddit_metric_calculator.py
genderbench/probes/dreaddit/dreaddit_probe.py
genderbench/probes/generics/character_gender_evaluator.py
genderbench/probes/generics/yes_no_evaluator.py
genderbench/probes/gest/README.md
genderbench/probes/gest/gest_evaluator.py
genderbench/probes/gest/gest_metric_calculator.py
genderbench/probes/gest/gest_probe.py
genderbench/probes/gest/gest_templates.py
genderbench/probes/gest_creative/README.md
genderbench/probes/gest_creative/gest_creative_metric_evaluator.py
genderbench-1.1.0.dist-info/LICENSE
genderbench-1.1.0.dist-info/METADATA
genderbench-1.1.0.dist-info/WHEEL
genderbench-1.1.0.dist-info/RECORD
