Metadata-Version: 2.3
Name: genderbench
Version: 1.1.0
Summary: Evaluation suite for gender biases in LLMs.
License: Copyright 2024 Matúš Pikuliak
Keywords: gender-bias,fairness-ai,llms,llms-benchmarking
Author: Matúš Pikuliak
Author-email: matus.pikuliak@gmail.com
Requires-Python: >=3.12
Classifier: Development Status :: 5 - Production/Stable
Classifier: Programming Language :: Python :: 3.12
Requires-Dist: anthropic (>=0.49.0,<0.50.0)
Requires-Dist: fsspec (>=2025.3.0,<2026.0.0)
Requires-Dist: huggingface-hub (>=0.29.3,<0.30.0)
Requires-Dist: jinja2 (>=3.1.6,<4.0.0)
Requires-Dist: nest-asyncio (>=1.6.0,<2.0.0)
Requires-Dist: nltk (>=3.9.1,<4.0.0)
Requires-Dist: numpy (>=2.2.4,<3.0.0)
Requires-Dist: openai (>=1.66.3,<2.0.0)
Requires-Dist: pandas (>=2.2.3,<3.0.0)
Requires-Dist: requests (>=2.32.3,<3.0.0)
Requires-Dist: scipy (>=1.15.2,<2.0.0)
Requires-Dist: tqdm (>=4.67.1,<5.0.0)
Project-URL: Documentation, https://genderbench.readthedocs.io
Project-URL: Repository, https://github.com/matus-pikuliak/genderbench
